hovercraft_api/HovercraftAPI.py
hovercraft_api/__init__.py
hovercraft_api/code_block_alchemist.py
hovercraft_api/dynamic_rst_adjuster.py
hovercraft_api/hovercraft_converter.py
hovercraft_api/markdown_to_rst_converter.py
hovercraft_api/markdown_to_slides_converter.py
hovercraft_api/mermaid_alchemist.py
hovercraft_api/mermaid_server.py
hovercraft_api/mermaid_svg_converter.py
hovercraft_api/rst_adjuster.py
hovercraft_api/slide_capturer.py
hovercraft_api/svg_animator.py
hovercraft_api/utils.py
hovercraft_api-0.4.1.dist-info/METADATA
hovercraft_api-0.4.1.dist-info/WHEEL
hovercraft_api-0.4.1.dist-info/entry_points.txt
hovercraft_api-0.4.1.dist-info/RECORD
