Metadata-Version: 2.1
Name: hovercraft-api
Version: 0.4.1
Summary: 
Author: Maki
Author-email: sunwood.ai.labs@gmail.com
Requires-Python: >=3.10,<4.0
Classifier: Programming Language :: Python :: 3
Classifier: Programming Language :: Python :: 3.10
Classifier: Programming Language :: Python :: 3.11
Classifier: Programming Language :: Python :: 3.12
Requires-Dist: art (>=6.2,<7.0)
Requires-Dist: beautifulsoup4 (>=4.12.3,<5.0.0)
Requires-Dist: hovercraft (>=2.7,<3.0)
Requires-Dist: litellm (>=1.42.3,<2.0.0)
Requires-Dist: loguru (>=0.7.2,<0.8.0)
Requires-Dist: opencv-python (>=4.10.0.84,<5.0.0.0)
Requires-Dist: pandoc (>=2.3,<3.0)
Requires-Dist: python-dotenv (>=1.0.1,<2.0.0)
Requires-Dist: selenium (>=4.23.1,<5.0.0)
Requires-Dist: tqdm (>=4.66.4,<5.0.0)
